[
  {
    "kanji": "京都",
    "hiragana": "きょうと",
    "type": "proper-noun",
    "english": "Kyoto"
  },
  {
    "kanji": "東京駅",
    "hiragana": "とうきょうえき",
    "type": "proper-noun",
    "english": "Tokyo Station"
  },
  {
    "kanji": "札幌市",
    "hiragana": "さっぽろし",
    "type": "proper-noun",
    "english": "Sapporo City"
  },
  {
    "kanji": "仙台市",
    "hiragana": "せんだいし",
    "type": "proper-noun",
    "english": "Sendai City"
  },
  {
    "kanji": "さいたま市",
    "hiragana": "さいたまし",
    "type": "proper-noun",
    "english": "Saitama City"
  },
  {
    "kanji": "千葉市",
    "hiragana": "ちばし",
    "type": "proper-noun",
    "english": "Chiba City"
  },
  {
    "kanji": "横浜市",
    "hiragana": "よこはまし",
    "type": "proper-noun",
    "english": "Yokohama City"
  },
  {
    "kanji": "川崎市",
    "hiragana": "かわさきし",
    "type": "proper-noun",
    "english": "Kawasaki City"
  },
  {
    "kanji": "名古屋市",
    "hiragana": "なごやし",
    "type": "proper-noun",
    "english": "Nagoya City"
  },
  {
    "kanji": "京都市",
    "hiragana": "きょうとし",
    "type": "proper-noun",
    "english": "Kyoto City"
  },
  {
    "kanji": "大阪市",
    "hiragana": "おおさかし",
    "type": "proper-noun",
    "english": "Osaka City"
  },
  {
    "kanji": "神戸市",
    "hiragana": "こうべし",
    "type": "proper-noun",
    "english": "Kobe City"
  },
  {
    "kanji": "広島市",
    "hiragana": "ひろしまし",
    "type": "proper-noun",
    "english": "Hiroshima City"
  },
  {
    "kanji": "福岡市",
    "hiragana": "ふくおかし",
    "type": "proper-noun",
    "english": "Fukuoka City"
  },
  {
    "kanji": "那覇市",
    "hiragana": "なはし",
    "type": "proper-noun",
    "english": "Naha City"
  },
  {
    "kanji": "箱根町",
    "hiragana": "はこねまち",
    "type": "proper-noun",
    "english": "Hakone Town"
  },
  {
    "kanji": "軽井沢町",
    "hiragana": "かるいざわまち",
    "type": "proper-noun",
    "english": "Karuizawa Town"
  },
  {
    "kanji": "鎌倉市",
    "hiragana": "かまくらし",
    "type": "proper-noun",
    "english": "Kamakura City"
  },
  {
    "kanji": "日光市",
    "hiragana": "にっこうし",
    "type": "proper-noun",
    "english": "Nikko City"
  },
  {
    "kanji": "新宿駅",
    "hiragana": "しんじゅくえき",
    "type": "proper-noun",
    "english": "Shinjuku Station"
  },
  {
    "kanji": "渋谷駅",
    "hiragana": "しぶやえき",
    "type": "proper-noun",
    "english": "Shibuya Station"
  },
  {
    "kanji": "品川駅",
    "hiragana": "しながわえき",
    "type": "proper-noun",
    "english": "Shinagawa Station"
  },
  {
    "kanji": "横浜駅",
    "hiragana": "よこはまえき",
    "type": "proper-noun",
    "english": "Yokohama Station"
  },
  {
    "kanji": "名古屋駅",
    "hiragana": "なごやえき",
    "type": "proper-noun",
    "english": "Nagoya Station"
  },
  {
    "kanji": "京都駅",
    "hiragana": "きょうとえき",
    "type": "proper-noun",
    "english": "Kyoto Station"
  },
  {
    "kanji": "大阪駅",
    "hiragana": "おおさかえき",
    "type": "proper-noun",
    "english": "Osaka Station"
  },
  {
    "kanji": "博多駅",
    "hiragana": "はかたえき",
    "type": "proper-noun",
    "english": "Hakata Station"
  },
  {
    "kanji": "ニューヨーク",
    "hiragana": "ニューヨーク",
    "type": "proper-noun",
    "english": "New York"
  },
  {
    "kanji": "ハワイ",
    "hiragana": "ハワイ",
    "type": "proper-noun",
    "english": "Hawaii"
  },
  {
    "kanji": "熊本",
    "hiragana": "くまもと",
    "type": "proper-noun",
    "english": "Kumamoto (place name)"
  },
  {
    "kanji": "東京",
    "hiragana": "とうきょう",
    "type": "proper-noun",
    "english": "Tokyo (capital city)"
  }
]
